[
    { "url": "https://www.youtube.com/embed/w7jMdCNhLfs", "title": "WhatsApp Channel Ne Sab Expose Kar Diya 😱 | Last Day With Chotay Bhai and Baray Bhai 😔" },
    { "url": "https://www.youtube.com/embed/vZJASzdeH-s", "title": "Is Time Travel Possible? | @Round2hell | Netflix India" },
    { "url": "https://www.youtube.com/embed/w7jMdCNhLfs", "title": "WhatsApp Channel Ne Sab Expose Kar Diya 😱 | Last Day With Chotay Bhai and Baray Bhai 😔" },
    { "url": "https://www.youtube.com/embed/vZJASzdeH-s", "title": "Is Time Travel Possible? | @Round2hell | Netflix India" },
    { "url": "https://www.youtube.com/embed/w7jMdCNhLfs", "title": "WhatsApp Channel Ne Sab Expose Kar Diya 😱 | Last Day With Chotay Bhai and Baray Bhai 😔" },
    { "url": "https://www.youtube.com/embed/vZJASzdeH-s", "title": "Is Time Travel Possible? | @Round2hell | Netflix India" }
  ]
  